seatsio/__init__.py
seatsio/client.py
seatsio/domain.py
seatsio/exceptions.py
seatsio/httpClient.py
seatsio/region.py
seatsio/util.py
seatsio/charts/__init__.py
seatsio/charts/chartsClient.py
seatsio/charts/chartsRequest.py
seatsio/eventlog/__init__.py
seatsio/eventlog/eventLogClient.py
seatsio/events/__init__.py
seatsio/events/changeBestAvailableObjectStatusRequest.py
seatsio/events/changeObjectStatusRequest.py
seatsio/events/channelProperties.py
seatsio/events/channelsClient.py
seatsio/events/channelsRequests.py
seatsio/events/createMultipleEventsRequest.py
seatsio/events/createSingleEventRequest.py
seatsio/events/editForSaleConfigForEventsRequest.py
seatsio/events/editForSaleConfigRequest.py
seatsio/events/eventProperties.py
seatsio/events/eventsClient.py
seatsio/events/extraDataRequest.py
seatsio/events/forSaleRequest.py
seatsio/events/objectProperties.py
seatsio/events/overrideSeasonObjectStatusRequest.py
seatsio/events/statusChangeRequest.py
seatsio/events/updateEventRequest.py
seatsio/holdtokens/HoldTokenClient.py
seatsio/holdtokens/__init__.py
seatsio/pagination/__init__.py
seatsio/pagination/listableObjectsClient.py
seatsio/pagination/lister.py
seatsio/pagination/page.py
seatsio/pagination/pageFetcher.py
seatsio/pagination/pagedIterator.py
seatsio/reports/__init__.py
seatsio/reports/charts/__init__.py
seatsio/reports/charts/chartReports.py
seatsio/reports/events/__init__.py
seatsio/reports/events/eventReports.py
seatsio/reports/usage/__init__.py
seatsio/reports/usage/usageReports.py
seatsio/seasons/__init__.py
seatsio/seasons/seasonsClient.py
seatsio/seasons/updateSeasonRequest.py
seatsio/ticketBuyers/__init__.py
seatsio/ticketBuyers/addTicketBuyerIdsResponse.py
seatsio/ticketBuyers/removeTicketBuyerIdsResponse.py
seatsio/ticketBuyers/ticketBuyersClient.py
seatsio/workspaces/UpdateWorkspaceRequest.py
seatsio/workspaces/__init__.py
seatsio/workspaces/createWorkspaceRequest.py
seatsio/workspaces/workspacesClient.py
seatsio-83.4.0.dist-info/licenses/LICENSE
seatsio-83.4.0.dist-info/METADATA
seatsio-83.4.0.dist-info/WHEEL
seatsio-83.4.0.dist-info/top_level.txt
seatsio-83.4.0.dist-info/RECORD
