Metadata-Version: 2.4
Name: seatsio
Version: 83.4.0
Summary: The official Seats.io Python SDK
License-Expression: MIT
Project-URL: Repository, https://github.com/seatsio/seatsio-python/
Project-URL: Issues, https://github.com/seatsio/seatsio-python/issues
Requires-Python: >=3.9
License-File: LICENSE
Requires-Dist: requests<3.0,>=2.0
Requires-Dist: munch==4.0
Requires-Dist: jsonpickle<5.0,>=3.0
Requires-Dist: future==1.0.0
Dynamic: license-file
